Workbook
Name aporte: APP!$C$24
Name patrimonio: APP!$C$27
Name qtd_anos: APP!$C$25
Name rendimento_carteira: APP!$C$20
Name salario: APP!$C$19
Name sugestao_investimento: APP!$C$21
Name taxa_mensal: APP!$C$26

Sheet APP
B18: CONFIGURAÇÕES
B19: Salário | C19: 2000
B20: Rendimento Carteira | C20: 0.006
B21: Sugestão de Investimento (30%) | C21: =C19*30% -> 600
B23: INVESTIMENTO MENSAL
B24: Quanto investir por mês? | C24: 600
B25: Por Quantos Anos? | C25: 5
A26: 2 | B26: Taxa De Rendimento mensal? | C26: 0.01
A27: 5 | B27: patrimônio acumulado? | C27: =FV(taxa_mensal,qtd_anos*12,aporte*-1) -> 49001.802
A28: 10 | B28: Dividendos Mensais? | C28: =patrimonio*rendimento_carteira -> 294.01081
A29: 20
A30: 30 | B30: CENÁRIOS | D30: Dividendos
B31: Quanto em 2 anos? | C31: =FV($C$26,$A26*12,$C$24*-1) -> 16184.079 | D31: =C31*rendimento_carteira -> 97.104473
B32: Quanto em 5 anos? | C32: =FV($C$26,$A27*12,$C$24*-1) -> 49001.802 | D32: =C32*rendimento_carteira -> 294.01081
B33: Quanto em 10 anos? | C33: =FV($C$26,$A28*12,$C$24*-1) -> 138023.21 | D33: =C33*rendimento_carteira -> 828.13928
B34: Quanto em 20 anos? | C34: =FV($C$26,$A29*12,$C$24*-1) -> 593553.22 | D34: =C34*rendimento_carteira -> 3561.3193
B35: Quanto em 30 anos? | C35: =FV($C$26,$A30*12,$C$24*-1) -> 2096978.5 | D35: =C35*rendimento_carteira -> 12581.871
B37: PERFIL | C37: Agressivo
B38: VALOR A SER INVESTIDO POR MÊS | C38: =aporte -> 600
B40: TIPO DE FII | C40: Percentual sugerido | D40: Valores
B41: PAPEL | C41: =VLOOKUP($C$37&"-"&B41,Plan4!$A:$D,4,FALSE) -> 0.5 | D41: =C41*$C$38 -> 300
B42: TIJOLO | C42: =VLOOKUP($C$37&"-"&B42,Plan4!$A:$D,4,FALSE) -> 0.1 | D42: =C42*$C$38 -> 60
B43: HÍBRIDOS | C43: =VLOOKUP($C$37&"-"&B43,Plan4!$A:$D,4,FALSE) -> 0.05 | D43: =C43*$C$38 -> 30
B44: FOFs | C44: =VLOOKUP($C$37&"-"&B44,Plan4!$A:$D,4,FALSE) -> 0.05 | D44: =C44*$C$38 -> 30
B45: DESENVOLVIMENTO | C45: =VLOOKUP($C$37&"-"&B45,Plan4!$A:$D,4,FALSE) -> 0.2 | D45: =C45*$C$38 -> 120
B46: HOTELARIAS | C46: =VLOOKUP($C$37&"-"&B46,Plan4!$A:$D,4,FALSE) -> 0.1 | D46: =C46*$C$38 -> 60
D47: =aporte -> 600

Sheet Plan2

Sheet Plan3

Sheet Plan4
A2: CHAVE | B2: PERFIL | C2: TIPO DE FII | D2: % | G2: %
A3: =$B$3&"-"&C3 -> Conservador-PAPEL | B3: Conservador | C3: PAPEL | D3: 0.3 | F3: Moderado-TIJOLO | G3: =VLOOKUP(F3,$A:$D,4,FALSE) -> 0.35
A4: =$B$3&"-"&C4 -> Conservador-TIJOLO | B4: Conservador | C4: TIJOLO | D4: 0.5
A5: =$B$3&"-"&C5 -> Conservador-HÍBRIDOS | B5: Conservador | C5: HÍBRIDOS | D5: 0.1
A6: =$B$3&"-"&C6 -> Conservador-FOFs | B6: Conservador | C6: FOFs | D6: 0.1
A7: =$B$3&"-"&C7 -> Conservador-DESENVOLVIMENTO | B7: Conservador | C7: DESENVOLVIMENTO | D7: 0
A8: =$B$3&"-"&C8 -> Conservador-HOTELARIAS | B8: Conservador | C8: HOTELARIAS | D8: 0
A9: =$B$9&"-"&C9 -> Moderado-PAPEL | B9: Moderado | C9: PAPEL | D9: 0.32
A10: =$B$9&"-"&C10 -> Moderado-TIJOLO | B10: Moderado | C10: TIJOLO | D10: 0.35
A11: =$B$9&"-"&C11 -> Moderado-HÍBRIDOS | B11: Moderado | C11: HÍBRIDOS | D11: 0.08
A12: =$B$9&"-"&C12 -> Moderado-FOFs | B12: Moderado | C12: FOFs | D12: 0.05
A13: =$B$9&"-"&C13 -> Moderado-DESENVOLVIMENTO | B13: Moderado | C13: DESENVOLVIMENTO | D13: 0.1
A14: =$B$9&"-"&C14 -> Moderado-HOTELARIAS | B14: Moderado | C14: HOTELARIAS | D14: 0.1
A15: =$B$15&"-"&C15 -> Agressivo-PAPEL | B15: Agressivo | C15: PAPEL | D15: 0.5
A16: =$B$15&"-"&C16 -> Agressivo-TIJOLO | B16: Agressivo | C16: TIJOLO | D16: 0.1
A17: =$B$15&"-"&C17 -> Agressivo-HÍBRIDOS | B17: Agressivo | C17: HÍBRIDOS | D17: 0.05
A18: =$B$15&"-"&C18 -> Agressivo-FOFs | B18: Agressivo | C18: FOFs | D18: 0.05
A19: =$B$15&"-"&C19 -> Agressivo-DESENVOLVIMENTO | B19: Agressivo | C19: DESENVOLVIMENTO | D19: 0.2
A20: =$B$15&"-"&C20 -> Agressivo-HOTELARIAS | B20: Agressivo | C20: HOTELARIAS | D20: 0.1
